src/__init__.py
src/main.py
src/core/__init__.py
src/core/ai_assistant.py
src/core/app_controller.py
src/core/command_parser.py
src/core/gui_automation.py
src/core/local_speech_recognition.py
src/core/system_controller.py
src/core/voice_recognition.py
src/utils/__init__.py
src/utils/permissions.py
src/utils/status_display.py
jws_voice_assistant-1.0.2.dist-info/LICENSE
jws_voice_assistant-1.0.2.dist-info/METADATA
jws_voice_assistant-1.0.2.dist-info/WHEEL
jws_voice_assistant-1.0.2.dist-info/entry_points.txt
jws_voice_assistant-1.0.2.dist-info/top_level.txt
jws_voice_assistant-1.0.2.dist-info/RECORD
