Metadata-Version: 2.1
Name: jws-voice-assistant
Version: 1.0.2
Summary: 智能语音助手系统 - 类似钢铁侠中的贾维斯（JARVIS）
Home-page: https://github.com/yourusername/jws
Author: Jws Team
Author-email: jws@example.com
Project-URL: Documentation, https://github.com/yourusername/jws#readme
Project-URL: Source, https://github.com/yourusername/jws
Project-URL: Tracker, https://github.com/yourusername/jws/issues
Keywords: voice assistant,jarvis,speech recognition,macos,automation,ai
Classifier: Development Status :: 4 - Beta
Classifier: Intended Audience :: End Users/Desktop
Classifier: Topic :: Desktop Environment
Classifier: Topic :: Multimedia :: Sound/Audio :: Speech
Classifier: License :: OSI Approved :: MIT License
Classifier: Programming Language :: Python :: 3
Classifier: Programming Language :: Python :: 3.9
Classifier: Programming Language :: Python :: 3.10
Classifier: Programming Language :: Python :: 3.11
Classifier: Operating System :: MacOS
Requires-Python: >=3.9
License-File: LICENSE
Requires-Dist: SpeechRecognition>=3.10.0
Requires-Dist: pyttsx3>=2.90
Requires-Dist: gTTS>=2.4.0
Requires-Dist: PyAutoGUI>=0.9.54
Requires-Dist: loguru>=0.7.2
Requires-Dist: python-dotenv>=1.0.0
Requires-Dist: pyyaml>=6.0.1
Requires-Dist: requests>=2.31.0
Requires-Dist: google-generativeai>=0.3.0
Provides-Extra: full
Requires-Dist: pyobjc-framework-Quartz>=10.1; extra == "full"
Requires-Dist: pyobjc-framework-AppKit>=10.1; extra == "full"
Requires-Dist: pyaudio>=0.2.14; extra == "full"
Requires-Dist: sounddevice>=0.4.6; extra == "full"
Requires-Dist: numpy>=1.24.3; extra == "full"
Requires-Dist: openai>=1.3.0; extra == "full"
Requires-Dist: langchain>=0.0.350; extra == "full"
